papery/__init__.py
papery/engine.py
papery/page.py
papery/papery.py
papery/rendering.py
papery/serving.py
papery/sitemap.py
papery/sitemap_template.xml
papery/util.py
papery/validate.py
papery/data/sample/README.md
papery/data/sample/config.yml
papery/data/sample/files/robots.txt
papery/data/sample/pages/index.md
papery/data/sample/pages/index.yml
papery/data/sample/themes/default/assets/css/style.css
papery/data/sample/themes/default/templates/base.tmpl
papery/data/sample/themes/default/templates/footer.tmpl
papery/data/sample/themes/default/templates/page.tmpl
papery/lint_configs/config_schema.yaml
papery/lint_configs/markdownlint.yaml
papery/lint_configs/yamllint.yaml
papery-0.7.2.data/scripts/papery
papery-0.7.2.dist-info/LICENSE
papery-0.7.2.dist-info/METADATA
papery-0.7.2.dist-info/WHEEL
papery-0.7.2.dist-info/top_level.txt
papery-0.7.2.dist-info/RECORD
