Metadata-Version: 2.1
Name: papery
Version: 0.7.2
Summary: A simple static site generator - supports Markdown, YAML and JSON inputs and Jinja2 templating
Home-page: https://github.com/withletters/papery
Author: Xcoo, Inc.
Author-email: developer@xcoo.jp
License: Apache License 2.0
License-File: LICENSE
Requires-Dist: jinja2
Requires-Dist: markdown
Requires-Dist: pymdown-extensions
Requires-Dist: pyyaml
Requires-Dist: yamllint
Requires-Dist: jsonlint
Requires-Dist: pykwalify
